playwright_ui5_select/__init__.py
playwright_ui5_select/py.typed
playwright_ui5_select/import/ui5/.version
playwright_ui5_select/import/ui5/css.js
playwright_ui5_select/import/ui5/xpath.js
playwright_ui5_select-0.0.19.dist-info/METADATA
playwright_ui5_select-0.0.19.dist-info/WHEEL
playwright_ui5_select-0.0.19.dist-info/licenses/LICENSE
playwright_ui5_select-0.0.19.dist-info/RECORD
