Metadata-Version: 2.4
Name: playwright-ui5-select
Version: 0.0.19
Summary: Use UI5 selectors with Playwright
Project-URL: Repository, https://github.com/JamesYFC/playwright-ui5-select
Author-email: James <jyfchen57@yahoo.com.au>
License-Expression: MIT
License-File: LICENSE
Requires-Python: >=3.9
